legos.memes-0.3.8-py3.8-nspkg.pth
legos/memes.py
legos.memes-0.3.8.dist-info/LICENSE
legos.memes-0.3.8.dist-info/METADATA
legos.memes-0.3.8.dist-info/WHEEL
legos.memes-0.3.8.dist-info/namespace_packages.txt
legos.memes-0.3.8.dist-info/top_level.txt
legos.memes-0.3.8.dist-info/RECORD
