Metadata-Version: 2.1
Name: legos.memes
Version: 0.3.8
Summary: Meme generator using the memegen api
Home-page: https://github.com/drewpearce/legos.memes
Author: Drew Pearce
License: GPLv3
Platform: UNKNOWN
Classifier: License :: OSI Approved :: GNU General Public License v3 (GPLv3)
Classifier: Development Status :: 5 - Production/Stable
Classifier: Programming Language :: Python :: 3
Requires-Dist: legobot (<2.0.0,>=1.3.6)
